__init__.py
tetris/__init__.py
tetris/board.py
tetris/colours.py
tetris/command.py
tetris/direction.py
tetris/engine.py
tetris/main.py
tetris/main_cli.py
tetris/piece.py
tetris/point.py
tetris/scorer.py
tetris/statistics.py
tetris/utils.py
tetris/interface/__init__.py
tetris/interface/abstract.py
tetris/interface/cli.py
tetris/interface/pygame.py
tetris_py-0.0.17.dist-info/LICENSE
tetris_py-0.0.17.dist-info/METADATA
tetris_py-0.0.17.dist-info/NOTICE
tetris_py-0.0.17.dist-info/WHEEL
tetris_py-0.0.17.dist-info/entry_points.txt
tetris_py-0.0.17.dist-info/top_level.txt
tetris_py-0.0.17.dist-info/RECORD
