Metadata-Version: 2.1
Name: tetris-py
Version: 0.0.17
Summary: A Tetris game written in Python.
Author-email: Toma Popov <toma98@hotmail.co.uk>
License: Apache License
Project-URL: Homepage, https://github.com/tomapopov/tetris-py
Project-URL: Issues, https://github.com/tomapopov/tetris-py/issues
Classifier: Programming Language :: Python :: 3.9
Classifier: Programming Language :: Python :: 3.10
Classifier: Programming Language :: Python :: 3.11
Classifier: Programming Language :: Python :: 3.12
Classifier: License :: OSI Approved :: Apache Software License
Requires-Python: >=3.9
License-File: LICENSE
License-File: NOTICE
Requires-Dist: pygame
